{
  "timestamp": "2025-08-02T20:55:13.907171",
  "files_consolidated": 538,
  "empty_dirs_removed": 27,
  "moved_files": 538,
  "failed_moves": 0,
  "files_by_module": {
    "CONSCIOUSNESS": {
      "awareness": 5,
      "states": 18,
      "reflection": 75,
      "unified": 2
    },
    "MEMORY": {
      "causal": 14,
      "folds": 17,
      "temporal": 58,
      "consolidation": 11
    },
    "CORE": {
      "integration": 12,
      "glyph": 15,
      "symbolic": 70,
      "neural": 3
    },
    "GOVERNANCE": {
      "ethics": 64,
      "policy": 13,
      "guardian": 8,
      "oversight": 8
    },
    "BRIDGE": {
      "api": 47,
      "adapters": 1,
      "protocols": 16,
      "external": 1
    },
    "QIM": {
      "quantum_states": 51,
      "entanglement": 5,
      "bio": 11,
      "superposition": 1
    },
    "EMOTION": {
      "vad": 1,
      "regulation": 4,
      "mood": 6,
      "empathy": 1
    }
  }
}