{
  "schema_version": "2.0.0",
  "directory_metadata": {
    "path": "candidate/consciousness/quantum",
    "lane": "development",
    "purpose": "Directory containing 2 Python files and 0 subdirectories",
    "trinity_role": [
      "consciousness"
    ],
    "last_updated": "2025-09-20"
  },
  "component_inventory": {
    "python_files": [
      {
        "filename": "superposition_processor.py",
        "component_type": "UTILITY",
        "has_contract": true,
        "contract_path": "contracts/consciousness/superposition_processor.json",
        "dependencies": [],
        "exports": [
          "SuperpositionState",
          "QuantumGate",
          "QuantumState",
          "SuperpositionConfiguration",
          "QuantumSuperpositionProcessor",
          "IdentityCoherenceMonitor",
          "ConsciousnessAmplifier",
          "GuardianQuantumEthics",
          "update_probability",
          "apply_phase_shift",
          "measure_state",
          "get_system_status",
          "initialize",
          "calibrate",
          "enable_quantum_monitoring"
        ]
      },
      {
        "filename": "collapse_governance_system.py",
        "component_type": "UTILITY",
        "has_contract": true,
        "contract_path": "contracts/consciousness/collapse_governance_system.json",
        "dependencies": [],
        "exports": [
          "CollapseState",
          "EthicalTier",
          "MoralOption",
          "CollapseEvent",
          "TraceIndexEntry",
          "CollapseHashSystem",
          "DriftScoreCalculator",
          "EthicalVault",
          "CollapseGovernanceSystem",
          "create_collapse_governance_system",
          "create_ethical_hash",
          "verify_ethical_integrity",
          "calculate_drift_score",
          "get_drift_prevention_rate",
          "store_approved_solution",
          "retrieve_approved_solution"
        ]
      }
    ],
    "subdirectories": [],
    "documentation": []
  },
  "schema_references": [
    {
      "schema_name": "directory_index",
      "schema_path": "schemas/directory_index.schema.json",
      "validation_status": "valid"
    }
  ],
  "agent_guidance": {
    "recommended_approach": "Start with consciousness architecture documentation, then examine engines and processors",
    "key_files": [],
    "common_tasks": [],
    "prerequisites": [
      "Understanding of LUKHAS lane system",
      "Trinity Framework familiarity",
      "Consciousness architecture patterns"
    ],
    "avoid_patterns": [
      "Modifying contracts without validation",
      "Breaking lane boundaries",
      "Ignoring Trinity Framework integration"
    ]
  },
  "performance_metadata": {
    "component_count": 2,
    "estimated_complexity": "low",
    "consciousness_integration": "basic",
    "test_coverage": 85.0
  },
  "relationships": {
    "parent_directory": "candidate/consciousness",
    "related_directories": [],
    "constellation_cluster": "unknown",
    "dependency_weight": "moderate"
  }
}