{
  "schema_version": "2.0.0",
  "directory_metadata": {
    "path": "candidate/qi/safety",
    "lane": "development",
    "purpose": "Directory containing 19 Python files and 1 subdirectories",
    "trinity_role": [],
    "last_updated": "2025-09-20"
  },
  "component_inventory": {
    "python_files": [
      {
        "filename": "teq_gate_provenance.py",
        "component_type": "UTILITY",
        "has_contract": false,
        "contract_path": null,
        "dependencies": [],
        "exports": [
          "TEQWithProvenance",
          "demo",
          "run"
        ]
      },
      {
        "filename": "risk_orchestrator.py",
        "component_type": "UTILITY",
        "has_contract": false,
        "contract_path": null,
        "dependencies": [],
        "exports": [
          "RoutePlan",
          "RiskOrchestrator",
          "score",
          "route"
        ]
      },
      {
        "filename": "policy_mutate.py",
        "component_type": "UTILITY",
        "has_contract": false,
        "contract_path": null,
        "dependencies": [],
        "exports": [
          "fuzz",
          "main"
        ]
      },
      {
        "filename": "receipts_sink.py",
        "component_type": "UTILITY",
        "has_contract": false,
        "contract_path": null,
        "dependencies": [],
        "exports": [
          "SinkConfig",
          "ship_once",
          "main"
        ]
      },
      {
        "filename": "provenance_uploader.py",
        "component_type": "UTILITY",
        "has_contract": false,
        "contract_path": null,
        "dependencies": [],
        "exports": [
          "ProvenanceRecord",
          "Uploader",
          "LocalUploader",
          "S3Uploader",
          "GCSUploader",
          "sha256_file",
          "sha256_bytes",
          "guess_mime",
          "resolve_uploader",
          "record_artifact",
          "load_record_by_sha",
          "verify_artifact",
          "main",
          "put",
          "put",
          "put",
          "put"
        ]
      },
      {
        "filename": "ci_report.py",
        "component_type": "UTILITY",
        "has_contract": false,
        "contract_path": null,
        "dependencies": [],
        "exports": []
      },
      {
        "filename": "provenance_streamer.py",
        "component_type": "UTILITY",
        "has_contract": false,
        "contract_path": null,
        "dependencies": [],
        "exports": [
          "is_prov",
          "healthz",
          "stream_artifact",
          "gen",
          "gen"
        ]
      },
      {
        "filename": "policy_linter.py",
        "component_type": "UTILITY",
        "has_contract": false,
        "contract_path": null,
        "dependencies": [],
        "exports": [
          "lint"
        ]
      },
      {
        "filename": "constants.py",
        "component_type": "UTILITY",
        "has_contract": false,
        "contract_path": null,
        "dependencies": [],
        "exports": []
      },
      {
        "filename": "policy_report.py",
        "component_type": "UTILITY",
        "has_contract": false,
        "contract_path": null,
        "dependencies": [],
        "exports": []
      },
      {
        "filename": "provenance_receipts.py",
        "component_type": "UTILITY",
        "has_contract": false,
        "contract_path": null,
        "dependencies": [],
        "exports": []
      },
      {
        "filename": "teq_coupler.py",
        "component_type": "UTILITY",
        "has_contract": false,
        "contract_path": null,
        "dependencies": [],
        "exports": [
          "calibrated_gate",
          "emit_calibrated_receipt",
          "main"
        ]
      },
      {
        "filename": "teq_replay.py",
        "component_type": "UTILITY",
        "has_contract": false,
        "contract_path": null,
        "dependencies": [],
        "exports": []
      },
      {
        "filename": "ci_runner.py",
        "component_type": "UTILITY",
        "has_contract": false,
        "contract_path": null,
        "dependencies": [],
        "exports": [
          "run",
          "main",
          "step"
        ]
      },
      {
        "filename": "provenance_links.py",
        "component_type": "UTILITY",
        "has_contract": false,
        "contract_path": null,
        "dependencies": [],
        "exports": [
          "presign_url",
          "presign_for_record",
          "main"
        ]
      },
      {
        "filename": "teq_unified.py",
        "component_type": "UTILITY",
        "has_contract": false,
        "contract_path": null,
        "dependencies": [],
        "exports": []
      },
      {
        "filename": "pii.py",
        "component_type": "UTILITY",
        "has_contract": false,
        "contract_path": null,
        "dependencies": [],
        "exports": [
          "PIIHit",
          "detect_pii",
          "mask_pii"
        ]
      },
      {
        "filename": "provenance_proxy.py",
        "component_type": "UTILITY",
        "has_contract": false,
        "contract_path": null,
        "dependencies": [],
        "exports": [
          "healthz",
          "get_presigned_link",
          "download"
        ]
      },
      {
        "filename": "teq_gate.py",
        "component_type": "UTILITY",
        "has_contract": false,
        "contract_path": null,
        "dependencies": [],
        "exports": []
      }
    ],
    "subdirectories": [
      {
        "name": "policy_packs",
        "has_index": false,
        "purpose": "Subdirectory with 0 Python files",
        "component_count": 0
      }
    ],
    "documentation": [
      {
        "filename": "USER_MANUAL.md",
        "type": "other",
        "has_sync_header": false
      },
      {
        "filename": "REPLAY_GUIDE.md",
        "type": "other",
        "has_sync_header": false
      },
      {
        "filename": "DEV_MANUAL.md",
        "type": "other",
        "has_sync_header": false
      }
    ]
  },
  "schema_references": [
    {
      "schema_name": "directory_index",
      "schema_path": "schemas/directory_index.schema.json",
      "validation_status": "valid"
    }
  ],
  "agent_guidance": {
    "recommended_approach": "Begin with documentation files, then explore core components",
    "key_files": [],
    "common_tasks": [],
    "prerequisites": [
      "Understanding of LUKHAS lane system",
      "Trinity Framework familiarity"
    ],
    "avoid_patterns": [
      "Modifying contracts without validation",
      "Breaking lane boundaries",
      "Ignoring Trinity Framework integration"
    ]
  },
  "performance_metadata": {
    "component_count": 19,
    "estimated_complexity": "medium",
    "consciousness_integration": "none",
    "test_coverage": 85.0
  },
  "relationships": {
    "parent_directory": "candidate/qi",
    "related_directories": [],
    "constellation_cluster": "unknown",
    "dependency_weight": "moderate"
  }
}